Metadata-Version: 2.1
Name: tccseg
Version: 0.1.0
Summary: Thai Character Cluster segmentation python package
Home-page: https://github.com/tchayintr/tccseg
Author: Thodsaporn Chay-intr
Author-email: chayintr@lr.pi.titech.ac.jp
License: MIT
Keywords: tcc,segmentation,Thai
Platform: UNKNOWN
Classifier: Development Status :: 3 - Alpha
Classifier: Topic :: Software Development :: Build Tools
Classifier: License :: OSI Approved :: MIT License
Classifier: Programming Language :: Python :: 3.7
